LICENSE
MANIFEST.in
README.md
requirements.txt
setup.py
cert_schema/__init__.py
cert_schema/schema/1.1/certificate-schema-v1-1.json
cert_schema/schema/1.1/issuer-schema-v1-1.json
cert_schema/schema/1.2/assertion-1.2.json
cert_schema/schema/1.2/blockchain-certificate-1.2.json
cert_schema/schema/1.2/blockchain-receipt-1.2.json
cert_schema/schema/1.2/certificate-1.2.json
cert_schema/schema/1.2/certificate-document-1.2.json
cert_schema/schema/1.2/context.json
cert_schema/schema/1.2/issuer-1.2.json
cert_schema/schema/1.2/issuer-id-1.2.json
cert_schema/schema_tools/__init__.py
cert_schema/schema_tools/schema_validator.py
cert_schema_pastday.egg-info/PKG-INFO
cert_schema_pastday.egg-info/SOURCES.txt
cert_schema_pastday.egg-info/dependency_links.txt
cert_schema_pastday.egg-info/requires.txt
cert_schema_pastday.egg-info/top_level.txt
tests/__init__.py
tests/test_schema_validator.py