Metadata-Version: 1.0
Name: cert-schema-pastday
Version: 2.0b1
Summary: tools for working with blockchain certificates
Home-page: https://github.com/blockchain-certificates/cert-schema
Author: MIT Media Lab Blockchain Certificates
Author-email: info@blockcerts.org
License: MIT
Platform: UNKNOWN
